{
    "10M08SAE144C8G": {
        "E144": {
            "PIN_6": {"comment": "Bank1A VREFB1N0 IO ADC1IN1 DIFFIO_RX_L1n DIFFOUT_L1n Low_Speed", "source": "Max10 10M08SAE144C8G pinout.pdf"},
            "PIN_7": {"comment": "Bank1A VREFB1N0 IO ADC1IN2 DIFFIO_RX_L1p DIFFOUT_L1p Low_Speed", "source": "Max10 10M08SAE144C8G pinout.pdf"},
            "PIN_8": {"comment": "Bank1A VREFB1N0 IO ADC1IN3 DIFFIO RX L3n DIFFOUT L3n Low Speed", "source": "Max10 10M08SAE144C8G pinout.pdf"},
            "PIN_10": {"comment": "Bank1A VREFB1N0 IO ADC1IN4 DIFFIO_RX_L3p DIFFOUT_L3p Low_Speed", "source": "Max10 10M08SAE144C8G pinout.pdf"},
            "PIN_11": {"comment": "Bank1A VREFB1N0 IO ADC1IN5 DIFFIO_RX_L5n DIFFOUT_L5n Low_Speed", "source": "Max10 10M08SAE144C8G pinout.pdf"},
            "PIN_12": {"comment": "Bank1A VREFB1N0 IO ADC1IN6 DIFFIO RX L5p DIFFOUT L5p Low Speed", "source": "Max10 10M08SAE144C8G pinout.pdf"},
            "PIN_13": {"comment": "Bank1A VREFB1N0 IO ADC1IN7 DIFFIO_RX_L7n DIFFOUT_L7n Low_Speed", "source": "Max10 10M08SAE144C8G pinout.pdf"},
            "PIN_14": {"comment": "Bank1A VREFB1N0 IO ADC1IN8 DIFFIO_RX_L7p DIFFOUT_L7p Low_Speed", "source": "Max10 10M08SAE144C8G pinout.pdf"},
            "PIN_15": {"comment": "Bank1B VREFB1N0 IO JTAGEN", "source": "Max10 10M08SAE144C8G pinout.pdf"},
            "PIN_16": {"comment": "Bank1B VREFB1N0 IO TMS DIFFIO_RX_L11n DIFFOUT_L11n Low_Speed", "source": "Max10 10M08SAE144C8G pinout.pdf"},
            "PIN_17": {"comment": "Bank1B VREFB1N0 IO VREFB1N0", "source": "Max10 10M08SAE144C8G pinout.pdf"},
            "PIN_18": {"comment": "Bank1B VREFB1N0 IO TCK DIFFIO RX L11p DIFFOUT L11p Low Speed", "source": "Max10 10M08SAE144C8G pinout.pdf"},
            "PIN_19": {"comment": "Bank1B VREFB1N0 IO TDI DIFFIO_RX_L12n DIFFOUT_L12n Low_Speed", "source": "Max10 10M08SAE144C8G pinout.pdf"},
            "PIN_20": {"comment": "Bank1B VREFB1N0 IO TDO DIFFIO_RX_L12p DIFFOUT_L12p Low_Speed", "source": "Max10 10M08SAE144C8G pinout.pdf"},
            "PIN_21": {"comment": "Bank1B VREFB1N0 IO DIFFIO RX L14n DIFFOUT L14n Low Speed", "source": "Max10 10M08SAE144C8G pinout.pdf"},
            "PIN_22": {"comment": "Bank1B VREFB1N0 IO DIFFIO_RX_L14p DIFFOUT_L14p Low_Speed", "source": "Max10 10M08SAE144C8G pinout.pdf"},
            "PIN_24": {"comment": "Bank1B VREFB1N0 IO DIFFIO_RX_L16n DIFFOUT_L16n Low_Speed", "source": "Max10 10M08SAE144C8G pinout.pdf"},
            "PIN_25": {"comment": "Bank1B VREFB1N0 IO DIFFIO RX L16p DIFFOUT L16p Low Speed", "source": "Max10 10M08SAE144C8G pinout.pdf"},
            "PIN_26": {"comment": "Bank2 VREFB2N0 IO CLK0n DIFFIO_RX_L18n DIFFOUT_L18n High_Speed", "source": "Max10 10M08SAE144C8G pinout.pdf"},
            "PIN_27": {"comment": "Bank2 VREFB2N0 IO CLK0p DIFFIO_RX_L18p DIFFOUT_L18p High_Speed", "source": "Max10 10M08SAE144C8G pinout.pdf"},
            "PIN_28": {"comment": "Bank2 VREFB2N0 IO CLK1n DIFFIO RX L20n DIFFOUT L20n High Speed", "source": "Max10 10M08SAE144C8G pinout.pdf"},
            "PIN_29": {"comment": "Bank2 VREFB2N0 IO CLK1p DIFFIO_RX_L20p DIFFOUT_L20p High_Speed", "source": "Max10 10M08SAE144C8G pinout.pdf"},
            "PIN_30": {"comment": "Bank2 VREFB2N0 IO VREFB2N0", "source": "Max10 10M08SAE144C8G pinout.pdf"},
            "PIN_32": {"comment": "Bank2 VREFB2N0 IO PLL L CLKOUTn DIFFIO RX L27n DIFFOUT L27n High Speed", "source": "Max10 10M08SAE144C8G pinout.pdf"},
            "PIN_33": {"comment": "Bank2 VREFB2N0 IO PLL_L_CLKOUTp DIFFIO_RX_L27p DIFFOUT_L27p High_Speed", "source": "Max10 10M08SAE144C8G pinout.pdf"},
            "PIN_38": {"comment": "Bank3 VREFB3N0 IO DIFFIO_TX_RX_B1n DIFFOUT_B1n High_Speed", "source": "Max10 10M08SAE144C8G pinout.pdf"},
            "PIN_39": {"comment": "Bank3 VREFB3N0 IO DIFFIO TX RX B1p DIFFOUT B1p High Speed", "source": "Max10 10M08SAE144C8G pinout.pdf"},
            "PIN_41": {"comment": "Bank3 VREFB3N0 IO DIFFIO_TX_RX_B3n DIFFOUT_B3n High_Speed", "source": "Max10 10M08SAE144C8G pinout.pdf"},
            "PIN_43": {"comment": "Bank3 VREFB3N0 IO DIFFIO_TX_RX_B3p DIFFOUT_B3p High_Speed", "source": "Max10 10M08SAE144C8G pinout.pdf"},
            "PIN_44": {"comment": "Bank3 VREFB3N0 IO DIFFIO TX RX B5n DIFFOUT B5n High Speed", "source": "Max10 10M08SAE144C8G pinout.pdf"},
            "PIN_45": {"comment": "Bank3 VREFB3N0 IO DIFFIO_TX_RX_B5p DIFFOUT_B5p High_Speed", "source": "Max10 10M08SAE144C8G pinout.pdf"},
            "PIN_46": {"comment": "Bank3 VREFB3N0 IO DIFFIO_TX_RX_B7n DIFFOUT_B7n High_Speed", "source": "Max10 10M08SAE144C8G pinout.pdf"},
            "PIN_47": {"comment": "Bank3 VREFB3N0 IO DIFFIO TX RX B7p DIFFOUT B7p High Speed", "source": "Max10 10M08SAE144C8G pinout.pdf"},
            "PIN_50": {"comment": "Bank3 VREFB3N0 IO DIFFIO_TX_RX_B9n DIFFOUT_B9n High_Speed", "source": "Max10 10M08SAE144C8G pinout.pdf"},
            "PIN_48": {"comment": "Bank3 VREFB3N0 IO VREFB3N0", "source": "Max10 10M08SAE144C8G pinout.pdf"},
            "PIN_52": {"comment": "Bank3 VREFB3N0 IO DIFFIO TX RX B9p DIFFOUT B9p High Speed", "source": "Max10 10M08SAE144C8G pinout.pdf"},
            "PIN_54": {"comment": "Bank3 VREFB3N0 IO", "source": "Max10 10M08SAE144C8G pinout.pdf"},
            "PIN_55": {"comment": "Bank3 VREFB3N0 IO DIFFIO_TX_RX_B12n DIFFOUT_B12n High_Speed", "source": "Max10 10M08SAE144C8G pinout.pdf"},
            "PIN_56": {"comment": "Bank3 VREFB3N0 IO DIFFIO TX RX B12p DIFFOUT B12p High Speed", "source": "Max10 10M08SAE144C8G pinout.pdf"},
            "PIN_57": {"comment": "Bank3 VREFB3N0 IO DIFFIO_TX_RX_B14n DIFFOUT_B14n High_Speed", "source": "Max10 10M08SAE144C8G pinout.pdf"},
            "PIN_58": {"comment": "Bank3 VREFB3N0 IO DIFFIO_TX_RX_B14p DIFFOUT_B14p High_Speed", "source": "Max10 10M08SAE144C8G pinout.pdf"},
            "PIN_59": {"comment": "Bank3 VREFB3N0 IO DIFFIO TX RX B16n DIFFOUT B16n High Speed", "source": "Max10 10M08SAE144C8G pinout.pdf"},
            "PIN_60": {"comment": "Bank3 VREFB3N0 IO DIFFIO_TX_RX_B16p DIFFOUT_B16p High_Speed", "source": "Max10 10M08SAE144C8G pinout.pdf"},
            "PIN_61": {"comment": "Bank4 VREFB4N0 IO VREFB4N0", "source": "Max10 10M08SAE144C8G pinout.pdf"},
            "PIN_62": {"comment": "Bank4 VREFB4N0 IO", "source": "Max10 10M08SAE144C8G pinout.pdf"},
            "PIN_64": {"comment": "Bank4 VREFB4N0 IO DIFFIO_TX_RX_B23n DIFFOUT_B23n High_Speed", "source": "Max10 10M08SAE144C8G pinout.pdf"},
            "PIN_65": {"comment": "Bank4 VREFB4N0 IO DIFFIO_TX_RX_B23p DIFFOUT_B23p High_Speed", "source": "Max10 10M08SAE144C8G pinout.pdf"},
            "PIN_66": {"comment": "Bank4 VREFB4N0 IO", "source": "Max10 10M08SAE144C8G pinout.pdf"},
            "PIN_69": {"comment": "Bank4 VREFB4N0 IO DIFFIO_TX_RX_B27n DIFFOUT_B27n High_Speed", "source": "Max10 10M08SAE144C8G pinout.pdf"},
            "PIN_70": {"comment": "Bank4 VREFB4N0 IO DIFFIO_TX_RX_B27p DIFFOUT_B27p High_Speed", "source": "Max10 10M08SAE144C8G pinout.pdf"},
            "PIN_75": {"comment": "Bank5 VREFB5N0 IO DIFFIO RX R1p DIFFOUT R1p High Speed", "source": "Max10 10M08SAE144C8G pinout.pdf"},
            "PIN_74": {"comment": "Bank5 VREFB5N0 IO DIFFIO_RX_R2p DIFFOUT_R2p High_Speed", "source": "Max10 10M08SAE144C8G pinout.pdf"},
            "PIN_77": {"comment": "Bank5 VREFB5N0 IO DIFFIO_RX_R1n DIFFOUT_R1n High_Speed", "source": "Max10 10M08SAE144C8G pinout.pdf"},
            "PIN_76": {"comment": "Bank5 VREFB5N0 IO DIFFIO RX R2n DIFFOUT R2n High Speed", "source": "Max10 10M08SAE144C8G pinout.pdf"},
            "PIN_79": {"comment": "Bank5 VREFB5N0 IO DIFFIO_RX_R7p DIFFOUT_R7p High_Speed", "source": "Max10 10M08SAE144C8G pinout.pdf"},
            "PIN_78": {"comment": "Bank5 VREFB5N0 IO", "source": "Max10 10M08SAE144C8G pinout.pdf"},
            "PIN_81": {"comment": "Bank5 VREFB5N0 IO DIFFIO RX R7n DIFFOUT R7n High Speed", "source": "Max10 10M08SAE144C8G pinout.pdf"},
            "PIN_80": {"comment": "Bank5 VREFB5N0 IO VREFB5N0", "source": "Max10 10M08SAE144C8G pinout.pdf"},
            "PIN_85": {"comment": "Bank5 VREFB5N0 IO DIFFIO_RX_R10p DIFFOUT_R10p High_Speed", "source": "Max10 10M08SAE144C8G pinout.pdf"},
            "PIN_84": {"comment": "Bank5 VREFB5N0 IO DIFFIO RX R11p DIFFOUT R11p High Speed", "source": "Max10 10M08SAE144C8G pinout.pdf"},
            "PIN_87": {"comment": "Bank5 VREFB5N0 IO DIFFIO_RX_R10n DIFFOUT_R10n High_Speed", "source": "Max10 10M08SAE144C8G pinout.pdf"},
            "PIN_86": {"comment": "Bank5 VREFB5N0 IO DIFFIO_RX_R11n DIFFOUT_R11n High_Speed", "source": "Max10 10M08SAE144C8G pinout.pdf"},
            "PIN_88": {"comment": "Bank6 VREFB6N0 IO CLK2p DIFFIO RX R14p DIFFOUT R14p High Speed", "source": "Max10 10M08SAE144C8G pinout.pdf"},
            "PIN_89": {"comment": "Bank6 VREFB6N0 IO CLK2n DIFFIO_RX_R14n DIFFOUT_R14n High_Speed", "source": "Max10 10M08SAE144C8G pinout.pdf"},
            "PIN_90": {"comment": "Bank6 VREFB6N0 IO CLK3p DIFFIO_RX_R16p DIFFOUT_R16p High_Speed", "source": "Max10 10M08SAE144C8G pinout.pdf"},
            "PIN_91": {"comment": "Bank6 VREFB6N0 IO CLK3n DIFFIO RX R16n DIFFOUT R16n High Speed", "source": "Max10 10M08SAE144C8G pinout.pdf"},
            "PIN_92": {"comment": "Bank6 VREFB6N0 IO DIFFIO_RX_R18p DIFFOUT_R18p High_Speed", "source": "Max10 10M08SAE144C8G pinout.pdf"},
            "PIN_93": {"comment": "Bank6 VREFB6N0 IO DIFFIO_RX_R18n DIFFOUT_R18n High_Speed", "source": "Max10 10M08SAE144C8G pinout.pdf"},
            "PIN_96": {"comment": "Bank6 VREFB6N0 IO DPCLK3 DIFFIO RX R26p DIFFOUT R26p High Speed", "source": "Max10 10M08SAE144C8G pinout.pdf"},
            "PIN_97": {"comment": "Bank6 VREFB6N0 IO VREFB6N0", "source": "Max10 10M08SAE144C8G pinout.pdf"},
            "PIN_98": {"comment": "Bank6 VREFB6N0 IO DPCLK2 DIFFIO_RX_R26n DIFFOUT_R26n High_Speed", "source": "Max10 10M08SAE144C8G pinout.pdf"},
            "PIN_99": {"comment": "Bank6 VREFB6N0 IO DIFFIO RX R27p DIFFOUT R27p High Speed", "source": "Max10 10M08SAE144C8G pinout.pdf"},
            "PIN_100": {"comment": "Bank6 VREFB6N0 IO DIFFIO_RX_R28p DIFFOUT_R28p High_Speed", "source": "Max10 10M08SAE144C8G pinout.pdf"},
            "PIN_101": {"comment": "Bank6 VREFB6N0 IO DIFFIO_RX_R27n DIFFOUT_R27n High_Speed", "source": "Max10 10M08SAE144C8G pinout.pdf"},
            "PIN_102": {"comment": "Bank6 VREFB6N0 IO DIFFIO RX R28n DIFFOUT R28n High Speed", "source": "Max10 10M08SAE144C8G pinout.pdf"},
            "PIN_105": {"comment": "Bank6 VREFB6N0 IO DIFFIO_RX_R33p DIFFOUT_R33p High_Speed", "source": "Max10 10M08SAE144C8G pinout.pdf"},
            "PIN_106": {"comment": "Bank6 VREFB6N0 IO DIFFIO_RX_R33n DIFFOUT_R33n High_Speed", "source": "Max10 10M08SAE144C8G pinout.pdf"},
            "PIN_110": {"comment": "Bank7 VREFB7N0 IO DIFFIO RX T1p DIFFOUT T1p High Speed", "source": "Max10 10M08SAE144C8G pinout.pdf"},
            "PIN_111": {"comment": "Bank7 VREFB7N0 IO DIFFIO_RX_T1n DIFFOUT_T1n High_Speed", "source": "Max10 10M08SAE144C8G pinout.pdf"},
            "PIN_112": {"comment": "Bank7 VREFB7N0 IO VREFB7N0", "source": "Max10 10M08SAE144C8G pinout.pdf"},
            "PIN_113": {"comment": "Bank7 VREFB7N0 IO", "source": "Max10 10M08SAE144C8G pinout.pdf"},
            "PIN_114": {"comment": "Bank7 VREFB7N0 IO", "source": "Max10 10M08SAE144C8G pinout.pdf"},
            "PIN_118": {"comment": "Bank7 VREFB7N0 IO DIFFIO_RX_T10p DIFFOUT_T10p High_Speed", "source": "Max10 10M08SAE144C8G pinout.pdf"},
            "PIN_119": {"comment": "Bank7 VREFB7N0 IO DIFFIO RX T10n DIFFOUT T10n High Speed", "source": "Max10 10M08SAE144C8G pinout.pdf"},
            "PIN_120": {"comment": "Bank8 VREFB8N0 IO DIFFIO_RX_T16p DIFFOUT_T16p Low_Speed", "source": "Max10 10M08SAE144C8G pinout.pdf"},
            "PIN_121": {"comment": "Bank8 VREFB8N0 IO DEV_CLRn DIFFIO_RX_T16n DIFFOUT_T16n Low_Speed", "source": "Max10 10M08SAE144C8G pinout.pdf"},
            "PIN_122": {"comment": "Bank8 VREFB8N0 IO DEV OE", "source": "Max10 10M08SAE144C8G pinout.pdf"},
            "PIN_123": {"comment": "Bank8 VREFB8N0 IO VREFB8N0", "source": "Max10 10M08SAE144C8G pinout.pdf"},
            "PIN_126": {"comment": "Bank8 VREFB8N0 IO CONFIG_SEL", "source": "Max10 10M08SAE144C8G pinout.pdf"},
            "PIN_124": {"comment": "Bank8 VREFB8N0 IO DIFFIO_RX_T19p DIFFOUT_T19p Low_Speed", "source": "Max10 10M08SAE144C8G pinout.pdf"},
            "PIN_129": {"comment": "Bank8 VREFB8N0 Input only nCONFIG", "source": "Max10 10M08SAE144C8G pinout.pdf"},
            "PIN_127": {"comment": "Bank8 VREFB8N0 IO DIFFIO RX T19n DIFFOUT T19n Low Speed", "source": "Max10 10M08SAE144C8G pinout.pdf"},
            "PIN_130": {"comment": "Bank8 VREFB8N0 IO DIFFIO_RX_T20p DIFFOUT_T20p Low_Speed", "source": "Max10 10M08SAE144C8G pinout.pdf"},
            "PIN_131": {"comment": "Bank8 VREFB8N0 IO DIFFIO_RX_T20n DIFFOUT_T20n Low_Speed", "source": "Max10 10M08SAE144C8G pinout.pdf"},
            "PIN_132": {"comment": "Bank8 VREFB8N0 IO DIFFIO RX T22p DIFFOUT T22p Low Speed", "source": "Max10 10M08SAE144C8G pinout.pdf"},
            "PIN_134": {"comment": "Bank8 VREFB8N0 IO CRC_ERROR DIFFIO_RX_T22n DIFFOUT_T22n Low_Speed", "source": "Max10 10M08SAE144C8G pinout.pdf"},
            "PIN_135": {"comment": "Bank8 VREFB8N0 IO", "source": "Max10 10M08SAE144C8G pinout.pdf"},
            "PIN_136": {"comment": "Bank8 VREFB8N0 IO nSTATUS DIFFIO RX T24p DIFFOUT T24p Low Speed", "source": "Max10 10M08SAE144C8G pinout.pdf"},
            "PIN_138": {"comment": "Bank8 VREFB8N0 IO CONF_DONE DIFFIO_RX_T24n DIFFOUT_T24n Low_Speed", "source": "Max10 10M08SAE144C8G pinout.pdf"},
            "PIN_140": {"comment": "Bank8 VREFB8N0 IO DIFFIO_RX_T26p DIFFOUT_T26p Low_Speed", "source": "Max10 10M08SAE144C8G pinout.pdf"},
            "PIN_141": {"comment": "Bank8 VREFB8N0 IO DIFFIO RX T26n DIFFOUT T26n Low Speed", "source": "Max10 10M08SAE144C8G pinout.pdf"}
        },
        "M153": {
            "PIN_D2": {"comment": "Bank1A VREFB1N0 IO ADC1IN1 DIFFIO_RX_L1n DIFFOUT_L1n Low_Speed", "source": "Max10 10M08SAE144C8G pinout.pdf"},
            "PIN_C2": {"comment": "Bank1A VREFB1N0 IO ADC1IN2 DIFFIO_RX_L1p DIFFOUT_L1p Low_Speed", "source": "Max10 10M08SAE144C8G pinout.pdf"},
            "PIN_F5": {"comment": "Bank1A VREFB1N0 IO ADC1IN3 DIFFIO RX L3n DIFFOUT L3n Low Speed", "source": "Max10 10M08SAE144C8G pinout.pdf"},
            "PIN_G5": {"comment": "Bank1A VREFB1N0 IO ADC1IN4 DIFFIO_RX_L3p DIFFOUT_L3p Low_Speed", "source": "Max10 10M08SAE144C8G pinout.pdf"},
            "PIN_C1": {"comment": "Bank1A VREFB1N0 IO ADC1IN5 DIFFIO_RX_L5n DIFFOUT_L5n Low_Speed", "source": "Max10 10M08SAE144C8G pinout.pdf"},
            "PIN_B1": {"comment": "Bank1A VREFB1N0 IO ADC1IN6 DIFFIO RX L5p DIFFOUT L5p Low Speed", "source": "Max10 10M08SAE144C8G pinout.pdf"},
            "PIN_E1": {"comment": "Bank1A VREFB1N0 IO ADC1IN7 DIFFIO_RX_L7n DIFFOUT_L7n Low_Speed", "source": "Max10 10M08SAE144C8G pinout.pdf"},
            "PIN_E2": {"comment": "Bank1A VREFB1N0 IO ADC1IN8 DIFFIO_RX_L7p DIFFOUT_L7p Low_Speed", "source": "Max10 10M08SAE144C8G pinout.pdf"},
            "PIN_G7": {"comment": "Bank1B VREFB1N0 IO JTAGEN", "source": "Max10 10M08SAE144C8G pinout.pdf"},
            "PIN_G1": {"comment": "Bank1B VREFB1N0 IO TMS DIFFIO_RX_L11n DIFFOUT_L11n Low_Speed", "source": "Max10 10M08SAE144C8G pinout.pdf"},
            "PIN_G2": {"comment": "Bank1B VREFB1N0 IO VREFB1N0", "source": "Max10 10M08SAE144C8G pinout.pdf"},
            "PIN_J1": {"comment": "Bank1B VREFB1N0 IO TCK DIFFIO RX L11p DIFFOUT L11p Low Speed", "source": "Max10 10M08SAE144C8G pinout.pdf"},
            "PIN_H5": {"comment": "Bank1B VREFB1N0 IO TDI DIFFIO_RX_L12n DIFFOUT_L12n Low_Speed", "source": "Max10 10M08SAE144C8G pinout.pdf"},
            "PIN_H4": {"comment": "Bank1B VREFB1N0 IO TDO DIFFIO_RX_L12p DIFFOUT_L12p Low_Speed", "source": "Max10 10M08SAE144C8G pinout.pdf"},
            "PIN_H3": {"comment": "Bank1B VREFB1N0 IO DIFFIO RX L14n DIFFOUT L14n Low Speed", "source": "Max10 10M08SAE144C8G pinout.pdf"},
            "PIN_J2": {"comment": "Bank1B VREFB1N0 IO DIFFIO_RX_L14p DIFFOUT_L14p Low_Speed", "source": "Max10 10M08SAE144C8G pinout.pdf"},
            "PIN_L1": {"comment": "Bank1B VREFB1N0 IO DIFFIO_RX_L16n DIFFOUT_L16n Low_Speed", "source": "Max10 10M08SAE144C8G pinout.pdf"},
            "PIN_K2": {"comment": "Bank1B VREFB1N0 IO DIFFIO RX L16p DIFFOUT L16p Low Speed", "source": "Max10 10M08SAE144C8G pinout.pdf"},
            "PIN_J4": {"comment": "Bank2 VREFB2N0 IO CLK0n DIFFIO_RX_L18n DIFFOUT_L18n High_Speed", "source": "Max10 10M08SAE144C8G pinout.pdf"},
            "PIN_J5": {"comment": "Bank2 VREFB2N0 IO CLK0p DIFFIO_RX_L18p DIFFOUT_L18p High_Speed", "source": "Max10 10M08SAE144C8G pinout.pdf"},
            "PIN_K5": {"comment": "Bank2 VREFB2N0 IO CLK1n DIFFIO RX L20n DIFFOUT L20n High Speed", "source": "Max10 10M08SAE144C8G pinout.pdf"},
            "PIN_K4": {"comment": "Bank2 VREFB2N0 IO CLK1p DIFFIO_RX_L20p DIFFOUT_L20p High_Speed", "source": "Max10 10M08SAE144C8G pinout.pdf"},
            "PIN_L5": {"comment": "Bank2 VREFB2N0 IO DPCLK0 DIFFIO_RX_L22n DIFFOUT_L22n High_Speed", "source": "Max10 10M08SAE144C8G pinout.pdf"},
            "PIN_P1": {"comment": "Bank2 VREFB2N0 IO VREFB2N0", "source": "Max10 10M08SAE144C8G pinout.pdf"},
            "PIN_L4": {"comment": "Bank2 VREFB2N0 IO DPCLK1 DIFFIO_RX_L22p DIFFOUT_L22p High_Speed", "source": "Max10 10M08SAE144C8G pinout.pdf"},
            "PIN_R2": {"comment": "Bank2 VREFB2N0 IO", "source": "Max10 10M08SAE144C8G pinout.pdf"},
            "PIN_N1": {"comment": "Bank2 VREFB2N0 IO PLL L CLKOUTn DIFFIO RX L27n DIFFOUT L27n High Speed", "source": "Max10 10M08SAE144C8G pinout.pdf"},
            "PIN_P2": {"comment": "Bank2 VREFB2N0 IO PLL_L_CLKOUTp DIFFIO_RX_L27p DIFFOUT_L27p High_Speed", "source": "Max10 10M08SAE144C8G pinout.pdf"},
            "PIN_M4": {"comment": "Bank3 VREFB3N0 IO DIFFIO_TX_RX_B1n DIFFOUT_B1n High_Speed", "source": "Max10 10M08SAE144C8G pinout.pdf"},
            "PIN_P3": {"comment": "Bank3 VREFB3N0 IO DIFFIO RX B2n DIFFOUT B2n High Speed", "source": "Max10 10M08SAE144C8G pinout.pdf"},
            "PIN_M5": {"comment": "Bank3 VREFB3N0 IO DIFFIO_TX_RX_B1p DIFFOUT_B1p High_Speed", "source": "Max10 10M08SAE144C8G pinout.pdf"},
            "PIN_R3": {"comment": "Bank3 VREFB3N0 IO DIFFIO_RX_B2p DIFFOUT_B2p High_Speed", "source": "Max10 10M08SAE144C8G pinout.pdf"},
            "PIN_L6": {"comment": "Bank3 VREFB3N0 IO DIFFIO TX RX B3n DIFFOUT B3n High Speed", "source": "Max10 10M08SAE144C8G pinout.pdf"},
            "PIN_P4": {"comment": "Bank3 VREFB3N0 IO DIFFIO_RX_B4n DIFFOUT_B4n High_Speed", "source": "Max10 10M08SAE144C8G pinout.pdf"},
            "PIN_L7": {"comment": "Bank3 VREFB3N0 IO DIFFIO_TX_RX_B3p DIFFOUT_B3p High_Speed", "source": "Max10 10M08SAE144C8G pinout.pdf"},
            "PIN_R5": {"comment": "Bank3 VREFB3N0 IO DIFFIO RX B4p DIFFOUT B4p High Speed", "source": "Max10 10M08SAE144C8G pinout.pdf"},
            "PIN_P6": {"comment": "Bank3 VREFB3N0 IO DIFFIO_TX_RX_B5n DIFFOUT_B5n High_Speed", "source": "Max10 10M08SAE144C8G pinout.pdf"},
            "PIN_R7": {"comment": "Bank3 VREFB3N0 IO DIFFIO_RX_B6n DIFFOUT_B6n High_Speed", "source": "Max10 10M08SAE144C8G pinout.pdf"},
            "PIN_P7": {"comment": "Bank3 VREFB3N0 IO DIFFIO TX RX B5p DIFFOUT B5p High Speed", "source": "Max10 10M08SAE144C8G pinout.pdf"},
            "PIN_P8": {"comment": "Bank3 VREFB3N0 IO DIFFIO_RX_B6p DIFFOUT_B6p High_Speed", "source": "Max10 10M08SAE144C8G pinout.pdf"},
            "PIN_L8": {"comment": "Bank3 VREFB3N0 IO DIFFIO_TX_RX_B7n DIFFOUT_B7n High_Speed", "source": "Max10 10M08SAE144C8G pinout.pdf"},
            "PIN_P9": {"comment": "Bank3 VREFB3N0 IO DIFFIO RX B8n DIFFOUT B8n High Speed", "source": "Max10 10M08SAE144C8G pinout.pdf"},
            "PIN_M7": {"comment": "Bank3 VREFB3N0 IO DIFFIO_TX_RX_B7p DIFFOUT_B7p High_Speed", "source": "Max10 10M08SAE144C8G pinout.pdf"},
            "PIN_R9": {"comment": "Bank3 VREFB3N0 IO DIFFIO_RX_B8p DIFFOUT_B8p High_Speed", "source": "Max10 10M08SAE144C8G pinout.pdf"},
            "PIN_M8": {"comment": "Bank3 VREFB3N0 IO DIFFIO TX RX B9n DIFFOUT B9n High Speed", "source": "Max10 10M08SAE144C8G pinout.pdf"},
            "PIN_R11": {"comment": "Bank3 VREFB3N0 IO VREFB3N0", "source": "Max10 10M08SAE144C8G pinout.pdf"},
            "PIN_N8": {"comment": "Bank3 VREFB3N0 IO DIFFIO_TX_RX_B9p DIFFOUT_B9p High_Speed", "source": "Max10 10M08SAE144C8G pinout.pdf"},
            "PIN_P12": {"comment": "Bank3 VREFB3N0 IO", "source": "Max10 10M08SAE144C8G pinout.pdf"},
            "PIN_R14": {"comment": "Bank3 VREFB3N0 IO DIFFIO_TX_RX_B10n DIFFOUT_B10n High_Speed", "source": "Max10 10M08SAE144C8G pinout.pdf"},
            "PIN_P15": {"comment": "Bank3 VREFB3N0 IO DIFFIO_TX_RX_B10p DIFFOUT_B10p High_Speed", "source": "Max10 10M08SAE144C8G pinout.pdf"},
            "PIN_L9": {"comment": "Bank3 VREFB3N0 IO DIFFIO TX RX B12n DIFFOUT B12n High Speed", "source": "Max10 10M08SAE144C8G pinout.pdf"},
            "PIN_M9": {"comment": "Bank3 VREFB3N0 IO DIFFIO_TX_RX_B12p DIFFOUT_B12p High_Speed", "source": "Max10 10M08SAE144C8G pinout.pdf"},
            "PIN_L10": {"comment": "Bank3 VREFB3N0 IO DIFFIO_TX_RX_B14n DIFFOUT_B14n High_Speed", "source": "Max10 10M08SAE144C8G pinout.pdf"},
            "PIN_M11": {"comment": "Bank3 VREFB3N0 IO DIFFIO TX RX B14p DIFFOUT B14p High Speed", "source": "Max10 10M08SAE144C8G pinout.pdf"},
            "PIN_P14": {"comment": "Bank3 VREFB3N0 IO DIFFIO_TX_RX_B16n DIFFOUT_B16n High_Speed", "source": "Max10 10M08SAE144C8G pinout.pdf"},
            "PIN_R13": {"comment": "Bank3 VREFB3N0 IO DIFFIO_TX_RX_B16p DIFFOUT_B16p High_Speed", "source": "Max10 10M08SAE144C8G pinout.pdf"},
            "PIN_M12": {"comment": "Bank5 VREFB5N0 IO DIFFIO RX R1p DIFFOUT R1p High Speed", "source": "Max10 10M08SAE144C8G pinout.pdf"},
            "PIN_N15": {"comment": "Bank5 VREFB5N0 IO DIFFIO_RX_R2p DIFFOUT_R2p High_Speed", "source": "Max10 10M08SAE144C8G pinout.pdf"},
            "PIN_L11": {"comment": "Bank5 VREFB5N0 IO DIFFIO_RX_R1n DIFFOUT_R1n High_Speed", "source": "Max10 10M08SAE144C8G pinout.pdf"},
            "PIN_N14": {"comment": "Bank5 VREFB5N0 IO DIFFIO RX R2n DIFFOUT R2n High Speed", "source": "Max10 10M08SAE144C8G pinout.pdf"},
            "PIN_K11": {"comment": "Bank5 VREFB5N0 IO DIFFIO_RX_R7p DIFFOUT_R7p High_Speed", "source": "Max10 10M08SAE144C8G pinout.pdf"},
            "PIN_M14": {"comment": "Bank5 VREFB5N0 IO", "source": "Max10 10M08SAE144C8G pinout.pdf"},
            "PIN_K12": {"comment": "Bank5 VREFB5N0 IO DIFFIO RX R7n DIFFOUT R7n High Speed", "source": "Max10 10M08SAE144C8G pinout.pdf"},
            "PIN_L15": {"comment": "Bank5 VREFB5N0 IO VREFB5N0", "source": "Max10 10M08SAE144C8G pinout.pdf"},
            "PIN_J9": {"comment": "Bank5 VREFB5N0 IO DIFFIO_RX_R10p DIFFOUT_R10p High_Speed", "source": "Max10 10M08SAE144C8G pinout.pdf"},
            "PIN_K14": {"comment": "Bank5 VREFB5N0 IO DIFFIO RX R11p DIFFOUT R11p High Speed", "source": "Max10 10M08SAE144C8G pinout.pdf"},
            "PIN_J11": {"comment": "Bank5 VREFB5N0 IO DIFFIO_RX_R10n DIFFOUT_R10n High_Speed", "source": "Max10 10M08SAE144C8G pinout.pdf"},
            "PIN_J14": {"comment": "Bank5 VREFB5N0 IO DIFFIO_RX_R11n DIFFOUT_R11n High_Speed", "source": "Max10 10M08SAE144C8G pinout.pdf"},
            "PIN_J12": {"comment": "Bank6 VREFB6N0 IO CLK2p DIFFIO RX R14p DIFFOUT R14p High Speed", "source": "Max10 10M08SAE144C8G pinout.pdf"},
            "PIN_H11": {"comment": "Bank6 VREFB6N0 IO CLK2n DIFFIO_RX_R14n DIFFOUT_R14n High_Speed", "source": "Max10 10M08SAE144C8G pinout.pdf"},
            "PIN_H12": {"comment": "Bank6 VREFB6N0 IO CLK3p DIFFIO_RX_R16p DIFFOUT_R16p High_Speed", "source": "Max10 10M08SAE144C8G pinout.pdf"},
            "PIN_H13": {"comment": "Bank6 VREFB6N0 IO CLK3n DIFFIO RX R16n DIFFOUT R16n High Speed", "source": "Max10 10M08SAE144C8G pinout.pdf"},
            "PIN_J15": {"comment": "Bank6 VREFB6N0 IO DIFFIO_RX_R18p DIFFOUT_R18p High_Speed", "source": "Max10 10M08SAE144C8G pinout.pdf"},
            "PIN_G15": {"comment": "Bank6 VREFB6N0 IO DIFFIO_RX_R18n DIFFOUT_R18n High_Speed", "source": "Max10 10M08SAE144C8G pinout.pdf"},
            "PIN_G11": {"comment": "Bank6 VREFB6N0 IO DPCLK3 DIFFIO RX R26p DIFFOUT R26p High Speed", "source": "Max10 10M08SAE144C8G pinout.pdf"},
            "PIN_E15": {"comment": "Bank6 VREFB6N0 IO VREFB6N0", "source": "Max10 10M08SAE144C8G pinout.pdf"},
            "PIN_G12": {"comment": "Bank6 VREFB6N0 IO DPCLK2 DIFFIO_RX_R26n DIFFOUT_R26n High_Speed", "source": "Max10 10M08SAE144C8G pinout.pdf"},
            "PIN_E14": {"comment": "Bank6 VREFB6N0 IO", "source": "Max10 10M08SAE144C8G pinout.pdf"},
            "PIN_F11": {"comment": "Bank6 VREFB6N0 IO DIFFIO_RX_R27p DIFFOUT_R27p High_Speed", "source": "Max10 10M08SAE144C8G pinout.pdf"},
            "PIN_C15": {"comment": "Bank6 VREFB6N0 IO DIFFIO_RX_R28p DIFFOUT_R28p High_Speed", "source": "Max10 10M08SAE144C8G pinout.pdf"},
            "PIN_F12": {"comment": "Bank6 VREFB6N0 IO DIFFIO RX R27n DIFFOUT R27n High Speed", "source": "Max10 10M08SAE144C8G pinout.pdf"},
            "PIN_C14": {"comment": "Bank6 VREFB6N0 IO DIFFIO_RX_R28n DIFFOUT_R28n High_Speed", "source": "Max10 10M08SAE144C8G pinout.pdf"},
            "PIN_E11": {"comment": "Bank6 VREFB6N0 IO DIFFIO_RX_R33p DIFFOUT_R33p High_Speed", "source": "Max10 10M08SAE144C8G pinout.pdf"},
            "PIN_D12": {"comment": "Bank6 VREFB6N0 IO DIFFIO RX R33n DIFFOUT R33n High Speed", "source": "Max10 10M08SAE144C8G pinout.pdf"},
            "PIN_D11": {"comment": "Bank8 VREFB8N0 IO DIFFIO_RX_T14p DIFFOUT_T14p Low_Speed", "source": "Max10 10M08SAE144C8G pinout.pdf"},
            "PIN_B15": {"comment": "Bank8 VREFB8N0 IO DIFFIO_RX_T15p DIFFOUT_T15p Low_Speed", "source": "Max10 10M08SAE144C8G pinout.pdf"},
            "PIN_D10": {"comment": "Bank8 VREFB8N0 IO DIFFIO RX T14n DIFFOUT T14n Low Speed", "source": "Max10 10M08SAE144C8G pinout.pdf"},
            "PIN_B14": {"comment": "Bank8 VREFB8N0 IO DIFFIO_RX_T15n DIFFOUT_T15n Low_Speed", "source": "Max10 10M08SAE144C8G pinout.pdf"},
            "PIN_C8": {"comment": "Bank8 VREFB8N0 IO DIFFIO_RX_T16p DIFFOUT_T16p Low_Speed", "source": "Max10 10M08SAE144C8G pinout.pdf"},
            "PIN_B13": {"comment": "Bank8 VREFB8N0 IO DIFFIO_RX_T17p DIFFOUT_T17p Low_Speed", "source": "Max10 10M08SAE144C8G pinout.pdf"},
            "PIN_B8": {"comment": "Bank8 VREFB8N0 IO DEV_CLRn DIFFIO_RX_T16n DIFFOUT_T16n Low_Speed", "source": "Max10 10M08SAE144C8G pinout.pdf"},
            "PIN_A14": {"comment": "Bank8 VREFB8N0 IO DIFFIO RX T17n DIFFOUT T17n Low Speed", "source": "Max10 10M08SAE144C8G pinout.pdf"},
            "PIN_E10": {"comment": "Bank8 VREFB8N0 IO DEV_OE DIFFIO_RX_T18p DIFFOUT_T18p Low_Speed", "source": "Max10 10M08SAE144C8G pinout.pdf"},
            "PIN_E9": {"comment": "Bank8 VREFB8N0 IO DIFFIO_RX_T18n DIFFOUT_T18n Low_Speed", "source": "Max10 10M08SAE144C8G pinout.pdf"},
            "PIN_A13": {"comment": "Bank8 VREFB8N0 IO VREFB8N0", "source": "Max10 10M08SAE144C8G pinout.pdf"},
            "PIN_D8": {"comment": "Bank8 VREFB8N0 IO CONFIG_SEL", "source": "Max10 10M08SAE144C8G pinout.pdf"},
            "PIN_B12": {"comment": "Bank8 VREFB8N0 IO DIFFIO_RX_T19p DIFFOUT_T19p Low_Speed", "source": "Max10 10M08SAE144C8G pinout.pdf"},
            "PIN_E8": {"comment": "Bank8 VREFB8N0 Input only nCONFIG", "source": "Max10 10M08SAE144C8G pinout.pdf"},
            "PIN_B11": {"comment": "Bank8 VREFB8N0 IO DIFFIO_RX_T19n DIFFOUT_T19n Low_Speed", "source": "Max10 10M08SAE144C8G pinout.pdf"},
            "PIN_B7": {"comment": "Bank8 VREFB8N0 IO DIFFIO_RX_T20p DIFFOUT_T20p Low_Speed", "source": "Max10 10M08SAE144C8G pinout.pdf"},
            "PIN_A9": {"comment": "Bank8 VREFB8N0 IO DIFFIO RX T21p DIFFOUT T21p Low Speed", "source": "Max10 10M08SAE144C8G pinout.pdf"},
            "PIN_B6": {"comment": "Bank8 VREFB8N0 IO DIFFIO_RX_T20n DIFFOUT_T20n Low_Speed", "source": "Max10 10M08SAE144C8G pinout.pdf"},
            "PIN_A11": {"comment": "Bank8 VREFB8N0 IO DIFFIO_RX_T21n DIFFOUT_T21n Low_Speed", "source": "Max10 10M08SAE144C8G pinout.pdf"},
            "PIN_D7": {"comment": "Bank8 VREFB8N0 IO DIFFIO RX T22p DIFFOUT T22p Low Speed", "source": "Max10 10M08SAE144C8G pinout.pdf"},
            "PIN_A7": {"comment": "Bank8 VREFB8N0 IO DIFFIO_RX_T23p DIFFOUT_T23p Low_Speed", "source": "Max10 10M08SAE144C8G pinout.pdf"},
            "PIN_E7": {"comment": "Bank8 VREFB8N0 IO CRC_ERROR DIFFIO_RX_T22n DIFFOUT_T22n Low_Speed", "source": "Max10 10M08SAE144C8G pinout.pdf"},
            "PIN_A5": {"comment": "Bank8 VREFB8N0 IO DIFFIO RX T23n DIFFOUT T23n Low Speed", "source": "Max10 10M08SAE144C8G pinout.pdf"},
            "PIN_D6": {"comment": "Bank8 VREFB8N0 IO nSTATUS DIFFIO_RX_T24p DIFFOUT_T24p Low_Speed", "source": "Max10 10M08SAE144C8G pinout.pdf"},
            "PIN_B4": {"comment": "Bank8 VREFB8N0 IO", "source": "Max10 10M08SAE144C8G pinout.pdf"},
            "PIN_E6": {"comment": "Bank8 VREFB8N0 IO CONF DONE DIFFIO RX T24n DIFFOUT T24n Low Speed", "source": "Max10 10M08SAE144C8G pinout.pdf"},
            "PIN_A2": {"comment": "Bank8 VREFB8N0 IO DIFFIO_RX_T26p DIFFOUT_T26p Low_Speed", "source": "Max10 10M08SAE144C8G pinout.pdf"},
            "PIN_A3": {"comment": "Bank8 VREFB8N0 IO DIFFIO_RX_T26n DIFFOUT_T26n Low_Speed", "source": "Max10 10M08SAE144C8G pinout.pdf"}
        },
        "U169": {
            "PIN_D1": {"comment": "Bank1A VREFB1N0 IO ADC1IN1 DIFFIO RX L1n DIFFOUT L1n Low Speed", "source": "Max10 10M08SAE144C8G pinout.pdf"},
            "PIN_C2": {"comment": "Bank1A VREFB1N0 IO ADC1IN2 DIFFIO RX L1p DIFFOUT L1p Low Speed", "source": "Max10 10M08SAE144C8G pinout.pdf"},
            "PIN_E3": {"comment": "Bank1A VREFB1N0 IO ADC1IN3 DIFFIO RX L3n DIFFOUT L3n Low Speed", "source": "Max10 10M08SAE144C8G pinout.pdf"},
            "PIN_E4": {"comment": "Bank1A VREFB1N0 IO ADC1IN4 DIFFIO RX L3p DIFFOUT L3p Low Speed", "source": "Max10 10M08SAE144C8G pinout.pdf"},
            "PIN_C1": {"comment": "Bank1A VREFB1N0 IO ADC1IN5 DIFFIO RX L5n DIFFOUT L5n Low Speed", "source": "Max10 10M08SAE144C8G pinout.pdf"},
            "PIN_B1": {"comment": "Bank1A VREFB1N0 IO ADC1IN6 DIFFIO RX L5p DIFFOUT L5p Low Speed", "source": "Max10 10M08SAE144C8G pinout.pdf"},
            "PIN_F1": {"comment": "Bank1A VREFB1N0 IO ADC1IN7 DIFFIO RX L7n DIFFOUT L7n Low Speed", "source": "Max10 10M08SAE144C8G pinout.pdf"},
            "PIN_E1": {"comment": "Bank1A VREFB1N0 IO ADC1IN8 DIFFIO RX L7p DIFFOUT L7p Low Speed", "source": "Max10 10M08SAE144C8G pinout.pdf"},
            "PIN_E5": {"comment": "Bank1B VREFB1N0 IO JTAGEN", "source": "Max10 10M08SAE144C8G pinout.pdf"},
            "PIN_G1": {"comment": "Bank1B VREFB1N0 IO TMS DIFFIO RX L11n DIFFOUT L11n Low Speed", "source": "Max10 10M08SAE144C8G pinout.pdf"},
            "PIN_H1": {"comment": "Bank1B VREFB1N0 IO VREFB1N0", "source": "Max10 10M08SAE144C8G pinout.pdf"},
            "PIN_G2": {"comment": "Bank1B VREFB1N0 IO TCK DIFFIO RX L11p DIFFOUT L11p Low Speed", "source": "Max10 10M08SAE144C8G pinout.pdf"},
            "PIN_F5": {"comment": "Bank1B VREFB1N0 IO TDI DIFFIO RX L12n DIFFOUT L12n Low Speed", "source": "Max10 10M08SAE144C8G pinout.pdf"},
            "PIN_F6": {"comment": "Bank1B VREFB1N0 IO TDO DIFFIO RX L12p DIFFOUT L12p Low Speed", "source": "Max10 10M08SAE144C8G pinout.pdf"},
            "PIN_F4": {"comment": "Bank1B VREFB1N0 IO DIFFIO RX L14n DIFFOUT L14n Low Speed", "source": "Max10 10M08SAE144C8G pinout.pdf"},
            "PIN_G4": {"comment": "Bank1B VREFB1N0 IO DIFFIO RX L14p DIFFOUT L14p Low Speed", "source": "Max10 10M08SAE144C8G pinout.pdf"},
            "PIN_H2": {"comment": "Bank1B VREFB1N0 IO DIFFIO RX L16n DIFFOUT L16n Low Speed", "source": "Max10 10M08SAE144C8G pinout.pdf"},
            "PIN_H3": {"comment": "Bank1B VREFB1N0 IO DIFFIO RX L16p DIFFOUT L16p Low Speed", "source": "Max10 10M08SAE144C8G pinout.pdf"},
            "PIN_G5": {"comment": "Bank2 VREFB2N0 IO CLK0n DIFFIO RX L18n DIFFOUT L18n High Speed", "source": "Max10 10M08SAE144C8G pinout.pdf"},
            "PIN_J1": {"comment": "Bank2 VREFB2N0 IO DIFFIO RX L19n DIFFOUT L19n High Speed", "source": "Max10 10M08SAE144C8G pinout.pdf"},
            "PIN_H6": {"comment": "Bank2 VREFB2N0 IO CLK0p DIFFIO RX L18p DIFFOUT L18p High Speed", "source": "Max10 10M08SAE144C8G pinout.pdf"},
            "PIN_J2": {"comment": "Bank2 VREFB2N0 IO DIFFIO RX L19p DIFFOUT L19p High Speed", "source": "Max10 10M08SAE144C8G pinout.pdf"},
            "PIN_H5": {"comment": "Bank2 VREFB2N0 IO CLK1n DIFFIO RX L20n DIFFOUT L20n High Speed", "source": "Max10 10M08SAE144C8G pinout.pdf"},
            "PIN_M1": {"comment": "Bank2 VREFB2N0 IO DIFFIO RX L21n DIFFOUT L21n High Speed", "source": "Max10 10M08SAE144C8G pinout.pdf"},
            "PIN_H4": {"comment": "Bank2 VREFB2N0 IO CLK1p DIFFIO RX L20p DIFFOUT L20p High Speed", "source": "Max10 10M08SAE144C8G pinout.pdf"},
            "PIN_M2": {"comment": "Bank2 VREFB2N0 IO DIFFIO RX L21p DIFFOUT L21p High Speed", "source": "Max10 10M08SAE144C8G pinout.pdf"},
            "PIN_N2": {"comment": "Bank2 VREFB2N0 IO DPCLK0 DIFFIO RX L22n DIFFOUT L22n High Speed", "source": "Max10 10M08SAE144C8G pinout.pdf"},
            "PIN_L1": {"comment": "Bank2 VREFB2N0 IO VREFB2N0", "source": "Max10 10M08SAE144C8G pinout.pdf"},
            "PIN_N3": {"comment": "Bank2 VREFB2N0 IO DPCLK1 DIFFIO RX L22p DIFFOUT L22p High Speed", "source": "Max10 10M08SAE144C8G pinout.pdf"},
            "PIN_L2": {"comment": "Bank2 VREFB2N0 IO", "source": "Max10 10M08SAE144C8G pinout.pdf"},
            "PIN_M3": {"comment": "Bank2 VREFB2N0 IO PLL L CLKOUTn DIFFIO RX L27n DIFFOUT L27n High Speed", "source": "Max10 10M08SAE144C8G pinout.pdf"},
            "PIN_K1": {"comment": "Bank2 VREFB2N0 IO DIFFIO RX L28n DIFFOUT L28n High Speed", "source": "Max10 10M08SAE144C8G pinout.pdf"},
            "PIN_L3": {"comment": "Bank2 VREFB2N0 IO PLL L CLKOUTp DIFFIO RX L27p DIFFOUT L27p High Speed", "source": "Max10 10M08SAE144C8G pinout.pdf"},
            "PIN_K2": {"comment": "Bank2 VREFB2N0 IO DIFFIO RX L28p DIFFOUT L28p High Speed", "source": "Max10 10M08SAE144C8G pinout.pdf"},
            "PIN_L5": {"comment": "Bank3 VREFB3N0 IO DIFFIO TX RX B1n DIFFOUT B1n High Speed", "source": "Max10 10M08SAE144C8G pinout.pdf"},
            "PIN_M4": {"comment": "Bank3 VREFB3N0 IO DIFFIO RX B2n DIFFOUT B2n High Speed", "source": "Max10 10M08SAE144C8G pinout.pdf"},
            "PIN_L4": {"comment": "Bank3 VREFB3N0 IO DIFFIO TX RX B1p DIFFOUT B1p High Speed", "source": "Max10 10M08SAE144C8G pinout.pdf"},
            "PIN_M5": {"comment": "Bank3 VREFB3N0 IO DIFFIO RX B2p DIFFOUT B2p High Speed", "source": "Max10 10M08SAE144C8G pinout.pdf"},
            "PIN_K5": {"comment": "Bank3 VREFB3N0 IO DIFFIO TX RX B3n DIFFOUT B3n High Speed", "source": "Max10 10M08SAE144C8G pinout.pdf"},
            "PIN_N4": {"comment": "Bank3 VREFB3N0 IO DIFFIO RX B4n DIFFOUT B4n High Speed", "source": "Max10 10M08SAE144C8G pinout.pdf"},
            "PIN_J5": {"comment": "Bank3 VREFB3N0 IO DIFFIO TX RX B3p DIFFOUT B3p High Speed", "source": "Max10 10M08SAE144C8G pinout.pdf"},
            "PIN_N5": {"comment": "Bank3 VREFB3N0 IO DIFFIO RX B4p DIFFOUT B4p High Speed", "source": "Max10 10M08SAE144C8G pinout.pdf"},
            "PIN_N6": {"comment": "Bank3 VREFB3N0 IO DIFFIO TX RX B5n DIFFOUT B5n High Speed", "source": "Max10 10M08SAE144C8G pinout.pdf"},
            "PIN_N7": {"comment": "Bank3 VREFB3N0 IO DIFFIO RX B6n DIFFOUT B6n High Speed", "source": "Max10 10M08SAE144C8G pinout.pdf"},
            "PIN_M7": {"comment": "Bank3 VREFB3N0 IO DIFFIO TX RX B5p DIFFOUT B5p High Speed", "source": "Max10 10M08SAE144C8G pinout.pdf"},
            "PIN_N8": {"comment": "Bank3 VREFB3N0 IO DIFFIO RX B6p DIFFOUT B6p High Speed", "source": "Max10 10M08SAE144C8G pinout.pdf"},
            "PIN_J6": {"comment": "Bank3 VREFB3N0 IO DIFFIO TX RX B7n DIFFOUT B7n High Speed", "source": "Max10 10M08SAE144C8G pinout.pdf"},
            "PIN_M8": {"comment": "Bank3 VREFB3N0 IO DIFFIO RX B8n DIFFOUT B8n High Speed", "source": "Max10 10M08SAE144C8G pinout.pdf"},
            "PIN_K6": {"comment": "Bank3 VREFB3N0 IO DIFFIO TX RX B7p DIFFOUT B7p High Speed", "source": "Max10 10M08SAE144C8G pinout.pdf"},
            "PIN_M9": {"comment": "Bank3 VREFB3N0 IO DIFFIO RX B8p DIFFOUT B8p High Speed", "source": "Max10 10M08SAE144C8G pinout.pdf"},
            "PIN_J7": {"comment": "Bank3 VREFB3N0 IO DIFFIO TX RX B9n DIFFOUT B9n High Speed", "source": "Max10 10M08SAE144C8G pinout.pdf"},
            "PIN_N11": {"comment": "Bank3 VREFB3N0 IO VREFB3N0", "source": "Max10 10M08SAE144C8G pinout.pdf"},
            "PIN_K7": {"comment": "Bank3 VREFB3N0 IO DIFFIO TX RX B9p DIFFOUT B9p High Speed", "source": "Max10 10M08SAE144C8G pinout.pdf"},
            "PIN_N12": {"comment": "Bank3 VREFB3N0 IO", "source": "Max10 10M08SAE144C8G pinout.pdf"},
            "PIN_M13": {"comment": "Bank3 VREFB3N0 IO DIFFIO TX RX B10n DIFFOUT B10n High Speed", "source": "Max10 10M08SAE144C8G pinout.pdf"},
            "PIN_N10": {"comment": "Bank3 VREFB3N0 IO DIFFIO RX B11n DIFFOUT B11n High Speed", "source": "Max10 10M08SAE144C8G pinout.pdf"},
            "PIN_M12": {"comment": "Bank3 VREFB3N0 IO DIFFIO TX RX B10p DIFFOUT B10p High Speed", "source": "Max10 10M08SAE144C8G pinout.pdf"},
            "PIN_N9": {"comment": "Bank3 VREFB3N0 IO DIFFIO RX B11p DIFFOUT B11p High Speed", "source": "Max10 10M08SAE144C8G pinout.pdf"},
            "PIN_M11": {"comment": "Bank3 VREFB3N0 IO DIFFIO TX RX B12n DIFFOUT B12n High Speed", "source": "Max10 10M08SAE144C8G pinout.pdf"},
            "PIN_L11": {"comment": "Bank3 VREFB3N0 IO DIFFIO TX RX B12p DIFFOUT B12p High Speed", "source": "Max10 10M08SAE144C8G pinout.pdf"},
            "PIN_J8": {"comment": "Bank3 VREFB3N0 IO DIFFIO TX RX B14n DIFFOUT B14n High Speed", "source": "Max10 10M08SAE144C8G pinout.pdf"},
            "PIN_K8": {"comment": "Bank3 VREFB3N0 IO DIFFIO TX RX B14p DIFFOUT B14p High Speed", "source": "Max10 10M08SAE144C8G pinout.pdf"},
            "PIN_M10": {"comment": "Bank3 VREFB3N0 IO DIFFIO TX RX B16n DIFFOUT B16n High Speed", "source": "Max10 10M08SAE144C8G pinout.pdf"},
            "PIN_L10": {"comment": "Bank3 VREFB3N0 IO DIFFIO TX RX B16p DIFFOUT B16p High Speed", "source": "Max10 10M08SAE144C8G pinout.pdf"},
            "PIN_K10": {"comment": "Bank5 VREFB5N0 IO DIFFIO RX R1p DIFFOUT R1p High Speed", "source": "Max10 10M08SAE144C8G pinout.pdf"},
            "PIN_K11": {"comment": "Bank5 VREFB5N0 IO DIFFIO RX R2p DIFFOUT R2p High Speed", "source": "Max10 10M08SAE144C8G pinout.pdf"},
            "PIN_J10": {"comment": "Bank5 VREFB5N0 IO DIFFIO RX R1n DIFFOUT R1n High Speed", "source": "Max10 10M08SAE144C8G pinout.pdf"},
            "PIN_L12": {"comment": "Bank5 VREFB5N0 IO DIFFIO RX R2n DIFFOUT R2n High Speed", "source": "Max10 10M08SAE144C8G pinout.pdf"},
            "PIN_K12": {"comment": "Bank5 VREFB5N0 IO DIFFIO RX R7p DIFFOUT R7p High Speed", "source": "Max10 10M08SAE144C8G pinout.pdf"},
            "PIN_L13": {"comment": "Bank5 VREFB5N0 IO", "source": "Max10 10M08SAE144C8G pinout.pdf"},
            "PIN_J12": {"comment": "Bank5 VREFB5N0 IO DIFFIO RX R7n DIFFOUT R7n High Speed", "source": "Max10 10M08SAE144C8G pinout.pdf"},
            "PIN_K13": {"comment": "Bank5 VREFB5N0 IO VREFB5N0", "source": "Max10 10M08SAE144C8G pinout.pdf"},
            "PIN_J9": {"comment": "Bank5 VREFB5N0 IO DIFFIO RX R8p DIFFOUT R8p High Speed", "source": "Max10 10M08SAE144C8G pinout.pdf"},
            "PIN_J13": {"comment": "Bank5 VREFB5N0 IO DIFFIO RX R9p DIFFOUT R9p High Speed", "source": "Max10 10M08SAE144C8G pinout.pdf"},
            "PIN_H10": {"comment": "Bank5 VREFB5N0 IO DIFFIO RX R8n DIFFOUT R8n High Speed", "source": "Max10 10M08SAE144C8G pinout.pdf"},
            "PIN_H13": {"comment": "Bank5 VREFB5N0 IO DIFFIO RX R9n DIFFOUT R9n High Speed", "source": "Max10 10M08SAE144C8G pinout.pdf"},
            "PIN_H9": {"comment": "Bank5 VREFB5N0 IO DIFFIO RX R10p DIFFOUT R10p High Speed", "source": "Max10 10M08SAE144C8G pinout.pdf"},
            "PIN_G13": {"comment": "Bank5 VREFB5N0 IO DIFFIO RX R11p DIFFOUT R11p High Speed", "source": "Max10 10M08SAE144C8G pinout.pdf"},
            "PIN_H8": {"comment": "Bank5 VREFB5N0 IO DIFFIO RX R10n DIFFOUT R10n High Speed", "source": "Max10 10M08SAE144C8G pinout.pdf"},
            "PIN_G12": {"comment": "Bank5 VREFB5N0 IO DIFFIO RX R11n DIFFOUT R11n High Speed", "source": "Max10 10M08SAE144C8G pinout.pdf"},
            "PIN_G9": {"comment": "Bank6 VREFB6N0 IO CLK2p DIFFIO RX R14p DIFFOUT R14p High Speed", "source": "Max10 10M08SAE144C8G pinout.pdf"},
            "PIN_G10": {"comment": "Bank6 VREFB6N0 IO CLK2n DIFFIO RX R14n DIFFOUT R14n High Speed", "source": "Max10 10M08SAE144C8G pinout.pdf"},
            "PIN_F13": {"comment": "Bank6 VREFB6N0 IO CLK3p DIFFIO RX R16p DIFFOUT R16p High Speed", "source": "Max10 10M08SAE144C8G pinout.pdf"},
            "PIN_E13": {"comment": "Bank6 VREFB6N0 IO CLK3n DIFFIO RX R16n DIFFOUT R16n High Speed", "source": "Max10 10M08SAE144C8G pinout.pdf"},
            "PIN_F12": {"comment": "Bank6 VREFB6N0 IO DIFFIO RX R18p DIFFOUT R18p High Speed", "source": "Max10 10M08SAE144C8G pinout.pdf"},
            "PIN_E12": {"comment": "Bank6 VREFB6N0 IO DIFFIO RX R18n DIFFOUT R18n High Speed", "source": "Max10 10M08SAE144C8G pinout.pdf"},
            "PIN_F9": {"comment": "Bank6 VREFB6N0 IO DPCLK3 DIFFIO RX R26p DIFFOUT R26p High Speed", "source": "Max10 10M08SAE144C8G pinout.pdf"},
            "PIN_D13": {"comment": "Bank6 VREFB6N0 IO VREFB6N0", "source": "Max10 10M08SAE144C8G pinout.pdf"},
            "PIN_F10": {"comment": "Bank6 VREFB6N0 IO DPCLK2 DIFFIO RX R26n DIFFOUT R26n High Speed", "source": "Max10 10M08SAE144C8G pinout.pdf"},
            "PIN_C13": {"comment": "Bank6 VREFB6N0 IO", "source": "Max10 10M08SAE144C8G pinout.pdf"},
            "PIN_F8": {"comment": "Bank6 VREFB6N0 IO DIFFIO RX R27p DIFFOUT R27p High Speed", "source": "Max10 10M08SAE144C8G pinout.pdf"},
            "PIN_B12": {"comment": "Bank6 VREFB6N0 IO DIFFIO RX R28p DIFFOUT R28p High Speed", "source": "Max10 10M08SAE144C8G pinout.pdf"},
            "PIN_E9": {"comment": "Bank6 VREFB6N0 IO DIFFIO RX R27n DIFFOUT R27n High Speed", "source": "Max10 10M08SAE144C8G pinout.pdf"},
            "PIN_B11": {"comment": "Bank6 VREFB6N0 IO DIFFIO RX R28n DIFFOUT R28n High Speed", "source": "Max10 10M08SAE144C8G pinout.pdf"},
            "PIN_C12": {"comment": "Bank6 VREFB6N0 IO DIFFIO RX R29p DIFFOUT R29p High Speed", "source": "Max10 10M08SAE144C8G pinout.pdf"},
            "PIN_B13": {"comment": "Bank6 VREFB6N0 IO DIFFIO RX R30p DIFFOUT R30p High Speed", "source": "Max10 10M08SAE144C8G pinout.pdf"},
            "PIN_C11": {"comment": "Bank6 VREFB6N0 IO DIFFIO RX R29n DIFFOUT R29n High Speed", "source": "Max10 10M08SAE144C8G pinout.pdf"},
            "PIN_A12": {"comment": "Bank6 VREFB6N0 IO DIFFIO RX R30n DIFFOUT R30n High Speed", "source": "Max10 10M08SAE144C8G pinout.pdf"},
            "PIN_E10": {"comment": "Bank6 VREFB6N0 IO DIFFIO RX R31p DIFFOUT R31p High Speed", "source": "Max10 10M08SAE144C8G pinout.pdf"},
            "PIN_D9": {"comment": "Bank6 VREFB6N0 IO DIFFIO RX R31n DIFFOUT R31n High Speed", "source": "Max10 10M08SAE144C8G pinout.pdf"},
            "PIN_D12": {"comment": "Bank6 VREFB6N0 IO DIFFIO RX R33p DIFFOUT R33p High Speed", "source": "Max10 10M08SAE144C8G pinout.pdf"},
            "PIN_D11": {"comment": "Bank6 VREFB6N0 IO DIFFIO RX R33n DIFFOUT R33n High Speed", "source": "Max10 10M08SAE144C8G pinout.pdf"},
            "PIN_C10": {"comment": "Bank8 VREFB8N0 IO DIFFIO RX T14p DIFFOUT T14p Low Speed", "source": "Max10 10M08SAE144C8G pinout.pdf"},
            "PIN_A8": {"comment": "Bank8 VREFB8N0 IO DIFFIO RX T15p DIFFOUT T15p Low Speed", "source": "Max10 10M08SAE144C8G pinout.pdf"},
            "PIN_C9": {"comment": "Bank8 VREFB8N0 IO DIFFIO RX T14n DIFFOUT T14n Low Speed", "source": "Max10 10M08SAE144C8G pinout.pdf"},
            "PIN_A9": {"comment": "Bank8 VREFB8N0 IO DIFFIO RX T15n DIFFOUT T15n Low Speed", "source": "Max10 10M08SAE144C8G pinout.pdf"},
            "PIN_B10": {"comment": "Bank8 VREFB8N0 IO DIFFIO RX T16p DIFFOUT T16p Low Speed", "source": "Max10 10M08SAE144C8G pinout.pdf"},
            "PIN_A10": {"comment": "Bank8 VREFB8N0 IO DIFFIO RX T17p DIFFOUT T17p Low Speed", "source": "Max10 10M08SAE144C8G pinout.pdf"},
            "PIN_B9": {"comment": "Bank8 VREFB8N0 IO DEV CLRn DIFFIO RX T16n DIFFOUT T16n Low Speed", "source": "Max10 10M08SAE144C8G pinout.pdf"},
            "PIN_A11": {"comment": "Bank8 VREFB8N0 IO DIFFIO RX T17n DIFFOUT T17n Low Speed", "source": "Max10 10M08SAE144C8G pinout.pdf"},
            "PIN_D8": {"comment": "Bank8 VREFB8N0 IO DEV OE DIFFIO RX T18p DIFFOUT T18p Low Speed", "source": "Max10 10M08SAE144C8G pinout.pdf"},
            "PIN_E8": {"comment": "Bank8 VREFB8N0 IO DIFFIO RX T18n DIFFOUT T18n Low Speed", "source": "Max10 10M08SAE144C8G pinout.pdf"},
            "PIN_B7": {"comment": "Bank8 VREFB8N0 IO VREFB8N0", "source": "Max10 10M08SAE144C8G pinout.pdf"},
            "PIN_D7": {"comment": "Bank8 VREFB8N0 IO CONFIG SEL", "source": "Max10 10M08SAE144C8G pinout.pdf"},
            "PIN_A7": {"comment": "Bank8 VREFB8N0 IO DIFFIO RX T19p DIFFOUT T19p Low Speed", "source": "Max10 10M08SAE144C8G pinout.pdf"},
            "PIN_E7": {"comment": "Bank8 VREFB8N0 Input only nCONFIG", "source": "Max10 10M08SAE144C8G pinout.pdf"},
            "PIN_A6": {"comment": "Bank8 VREFB8N0 IO DIFFIO RX T19n DIFFOUT T19n Low Speed", "source": "Max10 10M08SAE144C8G pinout.pdf"},
            "PIN_B6": {"comment": "Bank8 VREFB8N0 IO DIFFIO RX T20p DIFFOUT T20p Low Speed", "source": "Max10 10M08SAE144C8G pinout.pdf"},
            "PIN_A4": {"comment": "Bank8 VREFB8N0 IO DIFFIO RX T21p DIFFOUT T21p Low Speed", "source": "Max10 10M08SAE144C8G pinout.pdf"},
            "PIN_B5": {"comment": "Bank8 VREFB8N0 IO DIFFIO RX T20n DIFFOUT T20n Low Speed", "source": "Max10 10M08SAE144C8G pinout.pdf"},
            "PIN_A3": {"comment": "Bank8 VREFB8N0 IO DIFFIO RX T21n DIFFOUT T21n Low Speed", "source": "Max10 10M08SAE144C8G pinout.pdf"},
            "PIN_E6": {"comment": "Bank8 VREFB8N0 IO DIFFIO RX T22p DIFFOUT T22p Low Speed", "source": "Max10 10M08SAE144C8G pinout.pdf"},
            "PIN_B3": {"comment": "Bank8 VREFB8N0 IO DIFFIO RX T23p DIFFOUT T23p Low Speed", "source": "Max10 10M08SAE144C8G pinout.pdf"},
            "PIN_D6": {"comment": "Bank8 VREFB8N0 IO CRC ERROR DIFFIO RX T22n DIFFOUT T22n Low Speed", "source": "Max10 10M08SAE144C8G pinout.pdf"},
            "PIN_B4": {"comment": "Bank8 VREFB8N0 IO DIFFIO RX T23n DIFFOUT T23n Low Speed", "source": "Max10 10M08SAE144C8G pinout.pdf"},
            "PIN_C4": {"comment": "Bank8 VREFB8N0 IO nSTATUS DIFFIO RX T24p DIFFOUT T24p Low Speed", "source": "Max10 10M08SAE144C8G pinout.pdf"},
            "PIN_A5": {"comment": "Bank8 VREFB8N0 IO", "source": "Max10 10M08SAE144C8G pinout.pdf"},
            "PIN_C5": {"comment": "Bank8 VREFB8N0 IO CONF DONE DIFFIO RX T24n DIFFOUT T24n Low Speed", "source": "Max10 10M08SAE144C8G pinout.pdf"},
            "PIN_A2": {"comment": "Bank8 VREFB8N0 IO DIFFIO RX T26p DIFFOUT T26p Low Speed", "source": "Max10 10M08SAE144C8G pinout.pdf"},
            "PIN_B2": {"comment": "Bank8 VREFB8N0 IO DIFFIO RX T26n DIFFOUT T26n Low Speed", "source": "Max10 10M08SAE144C8G pinout.pdf"}
        }
    }
}
